blackwall/UI.css
blackwall/app.py
blackwall/audit_mode.py
blackwall/command_line.py
blackwall/commands_definition.py
blackwall/emoji.py
blackwall/main.py
blackwall/messages.py
blackwall/modals.py
blackwall/notifications.py
blackwall/regex.py
blackwall/secret_scrubber.py
blackwall/settings.py
blackwall/submit_command.py
blackwall/system_info.py
blackwall/tabs.py
blackwall/api/dataset.py
blackwall/api/group.py
blackwall/api/keyrings.py
blackwall/api/permit.py
blackwall/api/resource.py
blackwall/api/setropts.py
blackwall/api/traits_base.py
blackwall/api/user.py
blackwall/panels/panel_mode.py
blackwall/panels/traits_ui.py
blackwall/panels/analysis/analysis.py
blackwall/panels/backout/backout.py
blackwall/panels/command_output/command_output.py
blackwall/panels/copy/copy.py
blackwall/panels/dataset/dataset.py
blackwall/panels/errors/history.py
blackwall/panels/group/group.py
blackwall/panels/keyrings/keyrings.py
blackwall/panels/permits/permits.py
blackwall/panels/resource/resource.py
blackwall/panels/search/results.py
blackwall/panels/search/search.py
blackwall/panels/search/search_backend.py
blackwall/panels/setropts/setropts.py
blackwall/panels/users/user.py
blackwall/panels/welcome/welcome.py
blackwall/panels/welcome/welcome_message.md
blackwall/screens/modal/confirmation.py
blackwall/screens/modal/refresh.py
blackwall/screens/modal/rvary.py
blackwall/screens/modal/warning.py
blackwall/state/group.py
blackwall/themes/theme_3270.py
blackwall/themes/theme_blackwall.py
blackwall/themes/theme_cynosure.py
blackwall-0.6.0.dist-info/licenses/LICENSE
blackwall-0.6.0.dist-info/METADATA
blackwall-0.6.0.dist-info/WHEEL
blackwall-0.6.0.dist-info/entry_points.txt
blackwall-0.6.0.dist-info/top_level.txt
blackwall-0.6.0.dist-info/RECORD
