Metadata-Version: 2.4
Name: blackwall
Version: 0.6.0
Summary: Blackwall Protocol for mainframe security administration
Author: Emma Skovgaard, Karoline Halberg Rasmussen
License:                     GNU GENERAL PUBLIC LICENSE
Project-URL: Repository, https://github.com/EmmasBox/blackwall-protocol
Project-URL: Source, https://github.com/EmmasBox/blackwall-protocol
Project-URL: Issues, https://github.com/EmmasBox/blackwall-protocol/issues
Project-URL: Pypi, https://pypi.org/project/blackwall/
Project-URL: Documentation, https://emmasbox.github.io/blackwall-protocol-docs/
Keywords: RACF,security,mainframe,zos,TUI,SEAR,ESM
Classifier: Topic :: Security
Classifier: Intended Audience :: System Administrators
Classifier: Development Status :: 3 - Alpha
Classifier: Environment :: Console
Classifier: Operating System :: POSIX
Classifier: Topic :: System :: Hardware :: Mainframes
Classifier: Programming Language :: Python :: 3 :: Only
Classifier: Programming Language :: Python :: 3.12
Classifier: Programming Language :: Python :: 3.13
Classifier: Typing :: Typed
Requires-Python: >=3.12
License-File: LICENSE
Requires-Dist: pysear==0.1.1; sys_platform == "zos"
Requires-Dist: textual>=3.3.0
Provides-Extra: images
Requires-Dist: qrcode>=8.1; extra == "images"
Requires-Dist: textual-image>=0.8.2; extra == "images"
Provides-Extra: dev
Requires-Dist: textual-dev>=1.7.0; extra == "dev"
Dynamic: license-file
